bhargava_swara/__init__.py
bhargava_swara/analyzer.py
bhargava_swara/carnatic_or_hindustani.py
bhargava_swara/cent_spectogram.py
bhargava_swara/chroma_spectogram.py
bhargava_swara/cqt_spectogram.py
bhargava_swara/mel_spectrogram.py
bhargava_swara/ornament_detection.py
bhargava_swara/ornamentation_detection.py
bhargava_swara/raga_recognition.py
bhargava_swara/real_time_full_analysis.py
bhargava_swara/synthesis_system.py
bhargava_swara/tala_recognition.py
bhargava_swara/tanpura_drone_generator.py
bhargava_swara/tempo_detection.py
bhargava_swara-0.0.15.dist-info/licenses/LICENSE.txt
bhargava_swara-0.0.15.dist-info/METADATA
bhargava_swara-0.0.15.dist-info/WHEEL
bhargava_swara-0.0.15.dist-info/top_level.txt
bhargava_swara-0.0.15.dist-info/RECORD
