Metadata-Version: 2.4
Name: bhargava_swara
Version: 0.0.15
Summary: A library for analysis and synthesis of Indian classical music
Home-page: 
Author: Kuchi Chaitanya Krishna Deepak
Author-email: kckdeepak29@gmail.com
License: MIT
Keywords: music,analysis,synthesis,carnatic,hindustani,indian classical music,raga,tala,spectograms,signal
Classifier: Development Status :: 5 - Production/Stable
Classifier: Intended Audience :: Education
Classifier: Programming Language :: Python :: 3
Classifier: License :: OSI Approved :: MIT License
Classifier: Operating System :: OS Independent
Requires-Python: >=3.6
License-File: LICENSE.txt
Requires-Dist: google-generativeai>=0.1.0
Requires-Dist: librosa>=0.10.0
Requires-Dist: matplotlib>=3.7.0
Requires-Dist: numpy>=1.24.0
Requires-Dist: seaborn>=0.11.0
Requires-Dist: sounddevice>=0.4.0
Requires-Dist: scipy>=1.10.0
Dynamic: author
Dynamic: author-email
Dynamic: classifier
Dynamic: description
Dynamic: description-content-type
Dynamic: keywords
Dynamic: license
Dynamic: license-file
Dynamic: requires-dist
Dynamic: requires-python
Dynamic: summary
